README
setup.py
django_hoptoad.egg-info/PKG-INFO
django_hoptoad.egg-info/SOURCES.txt
django_hoptoad.egg-info/dependency_links.txt
django_hoptoad.egg-info/top_level.txt
hoptoad/__init__.py
hoptoad/middleware.py
hoptoad/models.py
hoptoad/tests.py
hoptoad/threadpool.py