Metadata-Version: 1.1
Name: django-hoptoad
Version: 0.2
Summary: django-hoptoad is some simple Middleware for letting Django-driven websites report their errors to Hoptoad.
Home-page: http://stevelosh.com/projects/django-hoptoad/
Author: Steve Losh
Author-email: steve@stevelosh.com
License: UNKNOWN
Platform: UNKNOWN
Classifier: Development Status :: 4 - Beta
Classifier: Environment :: Web Environment
Classifier: Intended Audience :: Developers
Classifier: License :: OSI Approved
Classifier: Operating System :: OS Independent
Classifier: Framework :: Django
Classifier: Programming Language :: Python
Classifier: Programming Language :: Python :: 2.6
Requires: p
Requires: y
Requires: y
Requires: a
Requires: m
Requires: l
